cyberark_tpc_plugin_validator-0.10.0.dist-info/licenses/LICENSE
tpc_plugin_validator/__init__.py
tpc_plugin_validator/main.py
tpc_plugin_validator/validator.py
tpc_plugin_validator/rule_sets/__init__.py
tpc_plugin_validator/rule_sets/conditions_section_rule_set.py
tpc_plugin_validator/rule_sets/cpm_parameters_validation_section_rule_set.py
tpc_plugin_validator/rule_sets/debug_information_section_rule_set.py
tpc_plugin_validator/rule_sets/file_rule_set.py
tpc_plugin_validator/rule_sets/parameters_section_rule_set.py
tpc_plugin_validator/rule_sets/process_file_rule_set.py
tpc_plugin_validator/rule_sets/prompts_file_rule_set.py
tpc_plugin_validator/rule_sets/rule_set.py
tpc_plugin_validator/rule_sets/section_rule_set.py
tpc_plugin_validator/rule_sets/states_section_rule_set.py
tpc_plugin_validator/rule_sets/transitions_section_rule_set.py
tpc_plugin_validator/utilities/__init__.py
tpc_plugin_validator/utilities/exceptions.py
tpc_plugin_validator/utilities/invalid_words.py
tpc_plugin_validator/utilities/severity.py
tpc_plugin_validator/utilities/types.py
tpc_plugin_validator/utilities/validation_result.py
cyberark_tpc_plugin_validator-0.10.0.dist-info/METADATA
cyberark_tpc_plugin_validator-0.10.0.dist-info/WHEEL
cyberark_tpc_plugin_validator-0.10.0.dist-info/entry_points.txt
cyberark_tpc_plugin_validator-0.10.0.dist-info/top_level.txt
cyberark_tpc_plugin_validator-0.10.0.dist-info/RECORD
