Metadata-Version: 2.4
Name: cyberark-tpc-plugin-validator
Version: 0.10.0
Summary: A tool to help validate a custom TPC plugin.
Author-email: Peter McDonald <git@petermcdonald.co.uk>
License: MIT License
Project-URL: homepage, https://github.com/petermcd/CyberArk-TPC-Plugin-Validator
Project-URL: repository, https://github.com/petermcd/CyberArk-TPC-Plugin-Validator.git
Project-URL: issues, https://github.com/petermcd/CyberArk-TPC-Plugin-Validator/issues
Keywords: cyberark,validate,tpc
Classifier: Development Status :: 4 - Beta
Classifier: Programming Language :: Python
Classifier: Programming Language :: Python :: 3.11
Classifier: Programming Language :: Python :: 3.12
Classifier: Programming Language :: Python :: 3.13
Classifier: Programming Language :: Python :: 3.14
Classifier: Programming Language :: Python :: 3.15
Classifier: Topic :: Software Development :: Testing
Classifier: Typing :: Typed
Requires-Python: >=3.11
License-File: LICENSE
Requires-Dist: cyberark-tpc-plugin-parser>=0.3.1
Dynamic: license-file
